benchmarks/benchmark.py
pytket/extensions/custatevec/__init__.py
pytket/extensions/custatevec/_metadata.py
pytket/extensions/custatevec/apply.py
pytket/extensions/custatevec/custatevec.py
pytket/extensions/custatevec/dtype.py
pytket/extensions/custatevec/gate_classes.py
pytket/extensions/custatevec/gate_definitions.py
pytket/extensions/custatevec/handle.py
pytket/extensions/custatevec/logger.py
pytket/extensions/custatevec/py.typed
pytket/extensions/custatevec/statevector.py
pytket/extensions/custatevec/utils.py
pytket/extensions/custatevec/backends/__init__.py
pytket/extensions/custatevec/backends/custatevec_backend.py
pytket_custatevec-0.1.0.dist-info/licenses/LICENSE
tests/__init__.py
tests/conftest.py
tests/test_custatevec_backend.py
tests/test_utils.py
pytket_custatevec-0.1.0.dist-info/METADATA
pytket_custatevec-0.1.0.dist-info/WHEEL
pytket_custatevec-0.1.0.dist-info/top_level.txt
pytket_custatevec-0.1.0.dist-info/RECORD
