Metadata-Version: 2.4
Name: pytket-custatevec
Version: 0.1.0
Summary: Extension for pytket providing access to cuStateVec functionality.
Author-email: Fabian Finger <fabian.finger@quantinuum.com>, Gabriel Matos <gabriel.matos@quantinuum.com>, Pranav Kalidindi <pranav.kalidindi@quantinuum.com>
Project-URL: Repository, https://github.com/CQCL/pytket-custatevec.git
Requires-Python: >=3.10
License-File: LICENSE
Requires-Dist: pytket
Requires-Dist: cupy-cuda12x
Requires-Dist: cuquantum-python-cu12>=25.3.0
Requires-Dist: plotly>=6.5.0
Provides-Extra: dev
Requires-Dist: pre-commit>=4.4.0; extra == "dev"
Requires-Dist: pytest>=8.4.0; extra == "dev"
Requires-Dist: ruff>=0.14.0; extra == "dev"
Requires-Dist: mypy>=1.18.0; extra == "dev"
Provides-Extra: docs
Requires-Dist: mkdocs; extra == "docs"
Requires-Dist: mkdocs-material; extra == "docs"
Requires-Dist: mkdocstrings[python]; extra == "docs"
Requires-Dist: mike; extra == "docs"
Provides-Extra: test
Requires-Dist: pytest; extra == "test"
Requires-Dist: pytket-qiskit; extra == "test"
Requires-Dist: pytket-qulacs; extra == "test"
Dynamic: license-file
